<?xml version = '1.0' encoding = 'UTF-8'?>
<Relation class="oracle.dbtools.crest.model.design.logical.Relation" name="Relation_29" directorySegmentName="seg_0" id="23667059-EB2C-8CCF-4C8F-987AFFAEF77D">
<createdBy>guilh</createdBy>
<createdTime>2025-03-07 19:05:32 UTC</createdTime>
<ownerDesignName>Melhores_Compras_MER_Relacional</ownerDesignName>
<engineerTo>
<item key="A90DA39C-4E27-73AC-0D61-C016BA8E06F7" value="true"/>
</engineerTo>
<sourcePk>971E831B-1C1E-8C98-DCC3-75A3C7DA28A4</sourcePk>
<identifying>false</identifying>
<optionalSource>true</optionalSource>
<optionalTarget>true</optionalTarget>
<sourceCardinality>1</sourceCardinality>
<sourceEntity>177A033A-9282-0424-5B74-E02E85402A1B</sourceEntity>
<targetCardinalityString>*</targetCardinalityString>
<targetEntity>221BA63E-3880-2E15-D3E2-66E087364C1B</targetEntity>
<transferable>true</transferable>
<deleteRule>NO ACTION</deleteRule>
</Relation>